finance_mcp/__init__.py
finance_mcp/server.py
finance_mcp_server-1.1.0.dist-info/licenses/LICENSE
finance_mcp_server-1.1.0.dist-info/METADATA
finance_mcp_server-1.1.0.dist-info/WHEEL
finance_mcp_server-1.1.0.dist-info/entry_points.txt
finance_mcp_server-1.1.0.dist-info/top_level.txt
finance_mcp_server-1.1.0.dist-info/RECORD
