Metadata-Version: 2.4
Name: finance-mcp-server
Version: 1.1.0
Summary: MCP Server for Financial Data and Technical Indicators
Home-page: https://github.com/akshatbindal/finance-mcp-server
Author: Akshat Bindal
Author-email: Akshat Bindal <akshatbindal01@gmail.com>
License: MIT
Project-URL: Homepage, https://github.com/akshatbindal/finance-mcp-server
Project-URL: Repository, https://github.com/akshatbindal/finance-mcp-server
Project-URL: Issues, https://github.com/akshatbindal/finance-mcp-server/issues
Keywords: mcp,finance,stocks,technical-analysis
Classifier: Development Status :: 4 - Beta
Classifier: Intended Audience :: Developers
Classifier: License :: OSI Approved :: MIT License
Classifier: Programming Language :: Python :: 3
Classifier: Topic :: Office/Business :: Financial
Requires-Python: >=3.8
License-File: LICENSE
Requires-Dist: mcp
Requires-Dist: yfinance
Requires-Dist: pandas
Requires-Dist: ta
Dynamic: author
Dynamic: home-page
Dynamic: license-file
Dynamic: requires-python
